Lab00/codigos/punto1/Mar/semaforo.v
module semaforo (
    input clk,
    input rst,
    output reg green,
    output reg yellow, // Se deja una sola salida para el amarillo
    output reg red
);

localparam verde     = 2'b00,
           amarillo1 = 2'b01,
           rojo      = 2'b10,
           amarillo2 = 2'b11;
        
reg [1:0] estado;
reg [2:0] contador;

// Logica secuencial: transicion de estados
always @(posedge clk or posedge rst) begin
    if (rst) begin
        estado   <= verde;
        contador <= 0;
    end else begin
        case (estado)
            verde: begin
                if (contador == 4) begin
                    estado   <= amarillo1;
                    contador <= 0;
                end else begin
                    contador <= contador + 1;
                end
            end
            amarillo1: begin
                if (contador == 1) begin
                    estado   <= rojo;
                    contador <= 0;
                end else begin
                    contador <= contador + 1;
                end
            end
            rojo: begin
                if (contador == 3) begin
                    estado   <= amarillo2;
                    contador <= 0;
                end else begin
                    contador <= contador + 1;
                end
            end
            amarillo2: begin
                if (contador == 1) begin
                   estado   <= verde;
                   contador <= 0;
                end else begin
                    contador <= contador + 1;
                end
            end       
            default: begin
                estado   <= verde;
                contador <= 0;
            end
        endcase
    end
end

// Logica combinacional: salidas segun el estado actual
always @(*) begin
    green  = (estado == verde);
    // El LED amarillo se enciende tanto en la ida como en el regreso
    yellow = (estado == amarillo1) || (estado == amarillo2);
    red    = (estado == rojo);
end

endmodule

Lab00/codigos/punto1/Mar/main.v
// Testbench de simulacion
`include "semaforo.v"
module main;
    reg clk;
    reg rst;
    wire green;
    wire yellow; // Se reemplazan yellow1 y yellow2 por un solo yellow
    wire red;

    semaforo dut (
        .clk(clk),
        .rst(rst),
        .green(green),
        .yellow(yellow), // Conexión a la única salida amarilla del módulo
        .red(red)
    );

    initial begin
        clk = 1'b0;
        forever #5 clk = ~clk;
    end

    initial begin
        rst = 1'b1;
        #12 rst = 1'b0;

        // Se ajusta el número de repeticiones si deseas ver más de un ciclo completo
        repeat (28) begin
            @(posedge clk);
            #1;
            // Se actualiza el display para mostrar solo las 3 luces físicas
            $display("t=%0t green=%b yellow=%b red=%b",
                     $time, green, yellow, red);

            // Comprobación de seguridad actualizada para 3 luces
            if ((green + yellow + red) != 1)
                $display("ERROR: cantidad incorrecta de luces encendidas");
        end

        $finish;
    end

initial begin
  $dumpfile("ondas.vcd");
  $dumpvars(0, main);
end
endmodule

Lab00/codigos/punto1/Mar/ondas.vcd
$date
	Sat Sep 19 13:51:33 2026
$end
$version
	Icarus Verilog
$end
$timescale
	1s
$end
$scope module main $end
$var wire 1 ! yellow $end
$var wire 1 " red $end
$var wire 1 # green $end
$var reg 1 $ clk $end
$var reg 1 % rst $end
$scope module dut $end
$var wire 1 $ clk $end
$var wire 1 % rst $end
$var parameter 2 & amarillo1 $end
$var parameter 2 ' amarillo2 $end
$var parameter 2 ( rojo $end
$var parameter 2 ) verde $end
$var reg 3 * contador [2:0] $end
$var reg 2 + estado [1:0] $end
$var reg 1 # green $end
$var reg 1 " red $end
$var reg 1 ! yellow $end
$upscope $end
$upscope $end
$enddefinitions $end
$comment Show the parameter values. $end
$dumpall
b0 )
b10 (
b11 '
b1 &
$end
#0
$dumpvars
b0 +
b0 *
1%
0$
1#
0"
0!
$end
#5
1$
#10
0$
#12
0%
#15
b1 *
1$
#20
0$
#25
b10 *
1$
#30
0$
#35
b11 *
1$
#40
0$
#45
b100 *
1$
#50
0$
#55
1!
0#
b0 *
b1 +
1$
#60
0$
#65
b1 *
1$
#70
0$
#75
1"
0!
b0 *
b10 +
1$
#80
0$
#85
b1 *
1$
#90
0$
#95
b10 *
1$
#100
0$
#105
b11 *
1$
#110
0$
#115
0"
1!
b0 *
b11 +
1$
#120
0$
#125
b1 *
1$
#130
0$
#135
0!
1#
b0 *
b0 +
1$
#140
0$
#145
b1 *
1$
#150
0$
#155
b10 *
1$
#160
0$
#165
b11 *
1$
#170
0$
#175
b100 *
1$
#180
0$
#185
1!
0#
b0 *
b1 +
1$
#190
0$
#195
b1 *
1$
#200
0$
#205
1"
0!
b0 *
b10 +
1$
#210
0$
#215
b1 *
1$
#220
0$
#225
b10 *
1$
#230
0$
#235
b11 *
1$
#240
0$
#245
0"
1!
b0 *
b11 +
1$
#250
0$
#255
b1 *
1$
#260
0$
#265
0!
1#
b0 *
b0 +
1$
#270
0$
#275
b1 *
1$
#280
0$
#285
b10 *
1$
