Lab00/codigos/punto1/Mar/semaforo.v
module semaforo (
    input clk,
    input rst,
    output reg green,
    output reg yellow,
    output reg red
);

localparam verde    = 2'b00,
           amarillo = 2'b01,
           rojo     = 2'b10,
           amarillo2 = 2'b11;

reg [1:0] estado;
reg [2:0] contador;

// Logica secuencial: transicion de estados
always @(posedge clk or posedge rst) begin
    if (rst) begin
        estado   <= verde;
        contador <= 0;
    end else begin
        case (estado)
            verde: begin
                if (contador == 4) begin
                    estado   <= amarillo;
                    contador <= 0;
                end else begin
                    contador <= contador + 1;
                end
            end
            amarillo: begin
                if (contador == 1) begin
                    estado   <= rojo;
                    contador <= 0;
                end else begin
                    contador <= contador + 1;
                end
            end
            rojo: begin
                if (contador == 3) begin
                    estado   <= amarillo2;
                    contador <= 0;
                end else begin
                    contador <= contador + 1;
                end
            end
            amarillo2: begin
                if (contador == 1) begin
                    estado   <= verde;
                    contador <= 0;
                end else begin
                    contador <= contador + 1;
                end
            end
            default: estado <= verde;
        endcase
    end
end

// Logica combinacional: salidas segun el estado actual
always @(*) begin
    green  = (estado == verde);
    yellow = (estado == amarillo) || (estado == amarillo2); // corrección: las asignaciones lógicas que se ejecutan secuencialmente dentro de un bloque always evalúan la última instrucción, al poner yellow = (estado == amarillo2), justo abajo, la línea de arriba queda completamente anulada
    red    = (estado == rojo);
end

endmodule

Lab00/codigos/punto1/Mar/TBsemaforo.v
`timescale 1ns/1ps

module TBsemaforo;
    reg clk = 0;
    reg rst = 0;

    wire green;
    wire yellow;
    wire red;
    
    semaforo uut (
        .clk     (clk),
        .rst   (rst),
        .green(green),
        .yellow(yellow),
        .red(red)
    );

    always begin
        #5 clk = ~clk;
    end

    initial begin
        $dumpfile("TBsemaforo.vcd");
        $dumpvars(0, TBsemaforo);

        #5;
        rst = 1'b1;

        #5;
        rst = 0;

        #500;
        rst = 1'b1;

        #5
        rst = 0;

        #500;

        $finish;
    end
endmodule

Lab00/codigos/punto1/Mar/TBsemaforo.vcd
$date
	Sun Sep 13 11:08:32 2026
$end
$version
	Icarus Verilog
$end
$timescale
	1ps
$end
$scope module TBsemaforo $end
$var wire 1 ! yellow $end
$var wire 1 " red $end
$var wire 1 # green $end
$var reg 1 $ clk $end
$var reg 1 % rst $end
$scope module uut $end
$var wire 1 $ clk $end
$var wire 1 % rst $end
$var parameter 2 & amarillo $end
$var parameter 2 ' amarillo2 $end
$var parameter 2 ( rojo $end
$var parameter 2 ) verde $end
$var reg 3 * contador [2:0] $end
$var reg 2 + estado [1:0] $end
$var reg 1 # green $end
$var reg 1 " red $end
$var reg 1 ! yellow $end
$upscope $end
$upscope $end
$enddefinitions $end
$comment Show the parameter values. $end
$dumpall
b0 )
b10 (
b11 '
b1 &
$end
#0
$dumpvars
bx +
bx *
0%
0$
x#
x"
x!
$end
#5000
0"
0!
1#
b0 *
b0 +
1%
1$
#10000
0%
0$
#15000
b1 *
1$
#20000
0$
#25000
b10 *
1$
#30000
0$
#35000
b11 *
1$
#40000
0$
#45000
b100 *
1$
#50000
0$
#55000
1!
0#
b0 *
b1 +
1$
#60000
0$
#65000
b1 *
1$
#70000
0$
#75000
1"
0!
b0 *
b10 +
1$
#80000
0$
#85000
b1 *
1$
#90000
0$
#95000
b10 *
1$
#100000
0$
#105000
b11 *
1$
#110000
0$
#115000
0"
1!
b0 *
b11 +
1$
#120000
0$
#125000
b1 *
1$
#130000
0$
#135000
0!
1#
b0 *
b0 +
1$
#140000
0$
#145000
b1 *
1$
#150000
0$
#155000
b10 *
1$
#160000
0$
#165000
b11 *
1$
#170000
0$
#175000
b100 *
1$
#180000
0$
#185000
1!
0#
b0 *
b1 +
1$
#190000
0$
#195000
b1 *
1$
#200000
0$
#205000
1"
0!
b0 *
b10 +
1$
#210000
0$
#215000
b1 *
1$
#220000
0$
#225000
b10 *
1$
#230000
0$
#235000
b11 *
1$
#240000
0$
#245000
0"
1!
b0 *
b11 +
1$
#250000
0$
#255000
b1 *
1$
#260000
0$
#265000
0!
1#
b0 *
b0 +
1$
#270000
0$
#275000
b1 *
1$
#280000
0$
#285000
b10 *
1$
#290000
0$
#295000
b11 *
1$
#300000
0$
#305000
b100 *
1$
#310000
0$
#315000
1!
0#
b0 *
b1 +
1$
#320000
0$
#325000
b1 *
1$
#330000
0$
#335000
1"
0!
b0 *
b10 +
1$
#340000
0$
#345000
b1 *
1$
#350000
0$
#355000
b10 *
1$
#360000
0$
#365000
b11 *
1$
#370000
0$
#375000
0"
1!
b0 *
b11 +
1$
#380000
0$
#385000
b1 *
1$
#390000
0$
#395000
0!
1#
b0 *
b0 +
1$
#400000
0$
#405000
b1 *
1$
#410000
0$
#415000
b10 *
1$
#420000
0$
#425000
b11 *
1$
#430000
0$
#435000
b100 *
1$
#440000
0$
#445000
1!
0#
b0 *
b1 +
1$
#450000
0$
#455000
b1 *
1$
#460000
0$
#465000
1"
0!
b0 *
b10 +
1$
#470000
0$
#475000
b1 *
1$
#480000
0$
#485000
b10 *
1$
#490000
0$
#495000
b11 *
1$
#500000
0$
#505000
0"
1!
b0 *
b11 +
1$
#510000
0!
1#
b0 +
0$
1%
#515000
b1 *
1$
0%
#520000
0$
#525000
b10 *
1$
#530000
0$
#535000
b11 *
1$
#540000
0$
#545000
b100 *
1$
#550000
0$
#555000
1!
0#
b0 *
b1 +
1$
#560000
0$
#565000
b1 *
1$
#570000
0$
#575000
1"
0!
b0 *
b10 +
1$
#580000
0$
#585000
b1 *
1$
#590000
0$
#595000
b10 *
1$
#600000
0$
#605000
b11 *
1$
#610000
0$
#615000
0"
1!
b0 *
b11 +
1$
#620000
0$
#625000
b1 *
1$
#630000
0$
#635000
0!
1#
b0 *
b0 +
1$
#640000
0$
#645000
b1 *
1$
#650000
0$
#655000
b10 *
1$
#660000
0$
#665000
b11 *
1$
#670000
0$
#675000
b100 *
1$
#680000
0$
#685000
1!
0#
b0 *
b1 +
1$
#690000
0$
#695000
b1 *
1$
#700000
0$
#705000
1"
0!
b0 *
b10 +
1$
#710000
0$
#715000
b1 *
1$
#720000
0$
#725000
b10 *
1$
#730000
0$
#735000
b11 *
1$
#740000
0$
#745000
0"
1!
b0 *
b11 +
1$
#750000
0$
#755000
b1 *
1$
#760000
0$
#765000
0!
1#
b0 *
b0 +
1$
#770000
0$
#775000
b1 *
1$
#780000
0$
#785000
b10 *
1$
#790000
0$
#795000
b11 *
1$
#800000
0$
#805000
b100 *
1$
#810000
0$
#815000
1!
0#
b0 *
b1 +
1$
#820000
0$
#825000
b1 *
1$
#830000
0$
#835000
1"
0!
b0 *
b10 +
1$
#840000
0$
#845000
b1 *
1$
#850000
0$
#855000
b10 *
1$
#860000
0$
#865000
b11 *
1$
#870000
0$
#875000
0"
1!
b0 *
b11 +
1$
#880000
0$
#885000
b1 *
1$
#890000
0$
#895000
0!
1#
b0 *
b0 +
1$
#900000
0$
#905000
b1 *
1$
#910000
0$
#915000
b10 *
1$
#920000
0$
#925000
b11 *
1$
#930000
0$
#935000
b100 *
1$
#940000
0$
#945000
1!
0#
b0 *
b1 +
1$
#950000
0$
#955000
b1 *
1$
#960000
0$
#965000
1"
0!
b0 *
b10 +
1$
#970000
0$
#975000
b1 *
1$
#980000
0$
#985000
b10 *
1$
#990000
0$
#995000
b11 *
1$
#1000000
0$
#1005000
0"
1!
b0 *
b11 +
1$
#1010000
0$
#1015000
b1 *
1$
