Lab01/códigos/alu.v
// ALU secuencial controlada por una FSM. Lee el operando A, captura B y op mediante botones, y muestra el resultado en LEDs.

module alu #(
    // T3S: Límite de conteo para la ventana de espera.
    // En simulación se usa un valor pequeño (10). En FPGA física para 3s a 100MHz se usa 300_000_000.
    parameter T3S = 400000000
)(
    input            CLK,   // Reloj
    input      [3:0] SW,    // Primer operando A (4 switches)
    input      [5:0] BTN,   // Entradas de botones (5:0)
    output reg [3:0] LED,   // Salida principal a LEDs de 4 bits
    output reg       LED_R, // Indicador para resultado en operación AND
    output reg       LED_G, // Indicador para resultado en operación OR
    output reg       LED_B  // Indicador para resultado en operación XOR
);

    // Sincronizador de Entradas y Detector de Flanco de Subida

    reg [5:0] s0 = 6'b0, s1 = 6'b0, s1_prev = 6'b0;

    always @(posedge CLK) begin
        s0      <= BTN;
        s1      <= s0;
        s1_prev <= s1;
    end

    wire [5:0] pulse = s1 & ~s1_prev; // Pulso de 1 ciclo en el flanco de subida
    wire       anyp  = |pulse;        // '1' lógico si se presionó cualquier botón

    // Declaración de Estados y Registros Internos

    localparam IDLE = 3'd7; // Estado de reposo e inicio

    reg [3:0]  A    = 4'b0; // Registro para almacenamiento del operando A
    reg [3:0]  B    = 4'b0; // Registro para almacenamiento del operando B
    reg [1:0]  op   = 2'b0; // Registro para código de operación
    reg [2:0]  slot = IDLE; // Estado actual de la FSM (3 bits)
    reg [28:0] c    = 29'd0;// Contador de tiempo para las ventanas de espera

    reg wp; // Mantiene el pulso del botón esperado según la ventana actual

    // Selección Combinacional del Botón Esperado por Estado

    always @(*) begin 
        case (slot)
            3'd0: wp = pulse[3]; // Espera pulso para B[3]
            3'd1: wp = pulse[2]; // Espera pulso para B[2]
            3'd2: wp = pulse[1]; // Espera pulso para B[1]
            3'd3: wp = pulse[0]; // Espera pulso para B[0]
            3'd4: wp = pulse[4]; // Espera pulso para op[1]
            3'd5: wp = pulse[5]; // Espera pulso para op[0]
            default: wp = 1'b0;
        endcase
    end

    // FSM

    always @(posedge CLK) begin
        case (slot)
            // Estado Reposo: Carga A desde los switches y espera la pulsación inicial
            IDLE: begin
                A    <= SW;
                B    <= 4'b0000;
                op   <= 2'b00;
                c    <= 29'd0;
                
                if (pulse[3]) begin
                    B[3] <= 1'b1; // ERROR SOLUCIONADO: Registra B[3]=1 si se presionó el botón correspondiente
                    slot <= 3'd1; // Transiciona inmediatamente a la ventana de B[2]
                end else if (anyp) begin
                    slot <= 3'd1; // Si fue otro botón, mantiene B[3]=0 y avanza
                end
            end

            // Ventana para la captura del bit B[2]
            3'd1: begin 
                if (pulse[2] || c == T3S-1) begin
                    if (pulse[2]) B[2] <= 1'b1;
                    slot <= 3'd2;
                    c    <= 29'd0;
                end else c <= c + 1;
            end

            // Ventana para la captura del bit B[1]
            3'd2: begin 
                if (pulse[1] || c == T3S-1) begin
                    if (pulse[1]) B[1] <= 1'b1;
                    slot <= 3'd3;
                    c    <= 29'd0;
                end else c <= c + 1;
            end

            // Ventana para la captura del bit B[0]
            3'd3: begin 
                if (pulse[0] || c == T3S-1) begin
                    if (pulse[0]) B[0] <= 1'b1;
                    slot <= 3'd4;
                    c    <= 29'd0;
                end else c <= c + 1;
            end

            // Ventana para la captura del bit op[0]
            3'd4: begin 
                if (pulse[4] || c == T3S-1) begin
                    if (pulse[4]) op[0] <= 1'b1;
                    slot <= 3'd5;
                    c    <= 29'd0;
                end else c <= c + 1;
            end

            // Ventana para la captura del bit op[1]
            3'd5: begin 
                if (pulse[5] || c == T3S-1) begin
                    if (pulse[5]) op[1] <= 1'b1;
                    slot <= 3'd6;
                    c    <= 29'd0;
                end else c <= c + 1;
            end

            // Estado de Resultado: Muestra el cálculo realizado hasta recibir un reinicio
            3'd6: begin 
                if (anyp) slot <= IDLE;
            end

            default: slot <= IDLE;
        endcase
    end

    // Lógica Combinacional de Operaciones Arithmetic/Logic

    wire [3:0] sum_result = A + B; // Suma aritmética de 4 bits
    wire [3:0] and_result = A & B; // Operación lógica AND bit a bit
    wire [3:0] or_result  = A | B; // Operación lógica OR bit a bit
    wire [3:0] xor_result = A ^ B; // Operación lógica XOR bit a bit

    // Decodificación y Mapeo de Salidas

    always @(*) begin
        // Valores por defecto (se limpian en cada evaluación del bloque combinacional)
        LED   = 4'b0000;
        LED_R = 1'b0;
        LED_G = 1'b0;
        LED_B = 1'b0;

        case (slot)
            IDLE:             LED = A;           // Muestra A en switches
            3'd1: begin
                LED = B;
                LED_B = 1'b1;
                LED_R = 1'b1;
            end
            3'd2: begin
                LED = B;
                LED_R = 1'b1;
                LED_G = 1'b1;
                
            end
            3'd3: begin
                LED = B;
                LED_G = 1'b1;
                LED_B = 1'b1;
            end

            // Ventanas de captura de operación: prende RGB en Blanco como aviso
            3'd4, 3'd5: begin
                LED   = {2'b00, op};
                LED_R = 1'b1;
                LED_G = 1'b1;
                LED_B = 1'b1;
            end
            // Ventanas de captura de operación: prende RGB en Blanco como aviso
            3'd4, 3'd5: begin
                LED   = {2'b00, op};
                LED_R = 1'b1;
                LED_G = 1'b1;
                LED_B = 1'b1;
            end

            // Estado de despliegue de resultado
            3'd6: begin
                case (op)
                    2'b00: begin
                        LED   = sum_result; // Suma
                    end
                    2'b01: begin
                        LED   = and_result;
                        LED_R = 1'b1;       // Solo Rojo
                    end
                    2'b10: begin
                        LED   = or_result;
                        LED_G = 1'b1;       // Solo Verde
                    end
                    2'b11: begin
                        LED   = xor_result;
                        LED_B = 1'b1;       // Solo Azul
                    end  
                endcase
            end

            default: ;
        endcase
    end

endmodule

Lab01/códigos/TBalu.v
`timescale 1ns / 1ps

module TBalu;

    reg        CLK;
    reg  [3:0] SW;
    reg  [5:0] BTN;
    wire [3:0] LED;
    wire       LED_R, LED_G, LED_B;

    // Instancia del módulo con T3S acelerado para simulación (10 ciclos = 100 ns por ventana)
    alu #(.T3S(10)) uut (
        .CLK(CLK),
        .SW(SW),
        .BTN(BTN),
        .LED(LED),
        .LED_R(LED_R),
        .LED_G(LED_G),
        .LED_B(LED_B)
    );

    // Generador de reloj (Periodo = 10 ns)
    always #5 CLK = ~CLK;

    initial begin
        // ---------- ARCHIVO DE ONDAS VCD ----------
        $dumpfile("TBalu.vcd");
        $dumpvars(0, TBalu);

        // Inicialización
        CLK = 0;
        SW  = 4'b0101; // A = 5
        BTN = 6'b0000;

        #20;
        // -------------------------------------------------------------------
        // 1. Pulso en BTN[3] -> B[3]=1 (Avanza a slot 1) [t = 20 ns]
        // -------------------------------------------------------------------
        BTN = 6'b001000; 
        #20;
        BTN = 6'b000000;

        // La FSM recorre automáticamente por timeout (100 ns cada uno):
        // slot 1 (B[2]) : t = 40ns  -> 140ns
        // slot 2 (B[1]) : t = 140ns -> 240ns
        // slot 3 (B[0]) : t = 240ns -> 340ns
        //
        // A los 340ns la FSM entra a slot 4 (espera op[1] mediante BTN[4])
        #310; // Avanzamos hasta t = 350 ns (dentro de slot 4)

        // -------------------------------------------------------------------
        // 2. Pulso en BTN[4] -> op[1]=1 (Configura op = 2'b10) [t = 350 ns]
        // -------------------------------------------------------------------
        BTN = 6'b010000; // Presiona BTN[4] para op[1]
        #20;
        BTN = 6'b000000;

        // Al presionar BTN[4], la FSM guarda op[1]=1 y avanza a slot 5 (op[0]).
        // Dejamos pasar la ventana slot 5 (~100 ns) por timeout para que op[0]=0.
        #200;

        $finish;
    end

endmodule

Lab01/códigos/TBalu.vcd
$date
	Wed Sep 23 16:47:12 2026
$end
$version
	Icarus Verilog
$end
$timescale
	1ps
$end
$scope module TBalu $end
$var wire 1 ! LED_R $end
$var wire 1 " LED_G $end
$var wire 1 # LED_B $end
$var wire 4 $ LED [3:0] $end
$var reg 6 % BTN [5:0] $end
$var reg 1 & CLK $end
$var reg 4 ' SW [3:0] $end
$scope module uut $end
$var wire 6 ( BTN [5:0] $end
$var wire 1 & CLK $end
$var wire 4 ) SW [3:0] $end
$var wire 4 * and_result [3:0] $end
$var wire 4 + or_result [3:0] $end
$var wire 6 , pulse [5:0] $end
$var wire 4 - xor_result [3:0] $end
$var wire 4 . sum_result [3:0] $end
$var wire 1 / anyp $end
$var parameter 3 0 IDLE $end
$var parameter 32 1 T3S $end
$var reg 4 2 A [3:0] $end
$var reg 4 3 B [3:0] $end
$var reg 4 4 LED [3:0] $end
$var reg 1 # LED_B $end
$var reg 1 " LED_G $end
$var reg 1 ! LED_R $end
$var reg 29 5 c [28:0] $end
$var reg 2 6 op [1:0] $end
$var reg 6 7 s0 [5:0] $end
$var reg 6 8 s1 [5:0] $end
$var reg 6 9 s1_prev [5:0] $end
$var reg 3 : slot [2:0] $end
$var reg 1 ; wp $end
$upscope $end
$upscope $end
$enddefinitions $end
$comment Show the parameter values. $end
$dumpall
b1010 1
b111 0
$end
#0
$dumpvars
0;
b111 :
b0 9
b0 8
b0 7
b0 6
b0 5
b0 4
b0 3
b0 2
0/
b0 .
b0 -
b0 ,
b0 +
b0 *
b101 )
b0 (
b101 '
0&
b0 %
b0 $
0#
0"
0!
$end
#5000
b101 $
b101 4
b101 -
b101 +
b101 .
b101 2
1&
#10000
0&
#15000
1&
#20000
0&
b1000 %
b1000 (
#25000
b1000 7
1&
#30000
0&
#35000
1/
b1000 ,
b1000 8
1&
#40000
0&
b0 %
b0 (
#45000
0/
b0 ,
b1000 $
b1000 4
b1101 -
b1101 +
b1000 9
b0 7
b1 :
b1101 .
b1000 3
1&
#50000
0&
#55000
b1 5
b0 8
1&
#60000
0&
#65000
b0 9
b10 5
1&
#70000
0&
#75000
b11 5
1&
#80000
0&
#85000
b100 5
1&
#90000
0&
#95000
b101 5
1&
#100000
0&
#105000
b110 5
1&
#110000
0&
#115000
b111 5
1&
#120000
0&
#125000
b1000 5
1&
#130000
0&
#135000
b1001 5
1&
#140000
0&
#145000
b1000 $
b1000 4
b0 5
b10 :
1&
#150000
0&
#155000
b1 5
1&
#160000
0&
#165000
b10 5
1&
#170000
0&
#175000
b11 5
1&
#180000
0&
#185000
b100 5
1&
#190000
0&
#195000
b101 5
1&
#200000
0&
#205000
b110 5
1&
#210000
0&
#215000
b111 5
1&
#220000
0&
#225000
b1000 5
1&
#230000
0&
#235000
b1001 5
1&
#240000
0&
#245000
b1000 $
b1000 4
b0 5
b11 :
1&
#250000
0&
#255000
b1 5
1&
#260000
0&
#265000
b10 5
1&
#270000
0&
#275000
b11 5
1&
#280000
0&
#285000
b100 5
1&
#290000
0&
#295000
b101 5
1&
#300000
0&
#305000
b110 5
1&
#310000
0&
#315000
b111 5
1&
#320000
0&
#325000
b1000 5
1&
#330000
0&
#335000
b1001 5
1&
#340000
0&
#345000
1#
1"
1!
b0 $
b0 4
b0 5
b100 :
1&
#350000
0&
b10000 %
b10000 (
#355000
b1 5
b10000 7
1&
#360000
0&
#365000
1;
1/
b10000 ,
b10000 8
b10 5
1&
#370000
0&
b0 %
b0 (
#375000
0/
b0 ,
0;
b1 $
b1 4
1#
1"
1!
b0 5
b101 :
b1 6
b10000 9
b0 7
1&
#380000
0&
#385000
b0 8
b1 5
1&
#390000
0&
#395000
b10 5
b0 9
1&
#400000
0&
#405000
b11 5
1&
#410000
0&
#415000
b100 5
1&
#420000
0&
#425000
b101 5
1&
#430000
0&
#435000
b110 5
1&
#440000
0&
#445000
b111 5
1&
#450000
0&
#455000
b1000 5
1&
#460000
0&
#465000
b1001 5
1&
#470000
0&
#475000
0#
0"
1!
b0 $
b0 4
b0 5
b110 :
1&
