Lab00/codigos/punto 3/Ana/TrasA.v
// Transmisor Serial Síncrono

module TrasA #(
    parameter CLKS_PER_BIT = 8 // Número de ciclos de reloj por bit transmitido, valor fijo para la simulación, pero puede ser parametrizado para diferentes velocidades de transmisión
)(
    input  CLK,     // Reloj 
    input  rst,     // Reset 
    input  wire [7:0] data_in, // Dato en paralelo a transmitir (8 bits)
    input  wire       start,   // Señal para iniciar
    output reg        busy,    // Transmisión en progreso
    output reg        tx,      // Salida serial (bit actual transmitido)
    output reg        done     // Señal de finalización
);

    // Registros 
    reg [2:0] bit_count;                       // Cuenta los bits enviados (0 a 7)
    reg [1:0] estado;                          // Estado de la FSM (son 4)
    reg [$clog2(CLKS_PER_BIT)-1:0] tick_cnt;   // "Cronómetro" variable por bit, funciona con un logaritmo para determinar el tamaño del registro según CLKS_PER_BIT
    reg [7:0] shift_reg;                       // Registro de desplazamiento PISO

    // Estados
    localparam IDLE     = 2'd0; 
    localparam LOAD     = 2'd1; 
    localparam TRANSMIT = 2'd2; 
    localparam DONE     = 2'd3; 

    // Inicio
    always @(posedge CLK or posedge rst) begin
        if (rst) begin
            // Reset, valores por defecto
            estado    <= IDLE;
            bit_count <= 3'd0;
            tick_cnt  <= 0;
            tx        <= 1'b1; // Línea en alto (inactiva)
            busy      <= 1'b0;
            done      <= 1'b0;
            shift_reg <= 8'd0;
        end
        else begin
            case (estado)
                IDLE: begin
                    done <= 1'b0; // Limpia
                    tx   <= 1'b1; // Mantiene la línea serial en nivel alto (Idle)
                    busy <= 1'b0; // Indica que está libre
                    
                    if (start) begin
                        estado <= LOAD; // Inicia
                    end
                end

                LOAD: begin
                    estado    <= TRANSMIT;
                    bit_count <= 3'd0;         // Conteo de bits desde 0
                    tick_cnt  <= 0;            // Reinicia el contador de tiempo
                    shift_reg <= data_in;      // Carga paralela del byte
                    busy      <= 1'b1;         // Sistema ocupado
                    done      <= 1'b0;         // Limpia
                    tx        <= data_in[0];   // Expone el bit LSB inmediatamente
                end

                TRANSMIT: begin
                    tx <= shift_reg[bit_count]; // Utiliza bit_count como puntero

                    if (tick_cnt == CLKS_PER_BIT - 1) begin
                        tick_cnt <= 0;
                        
                        if (bit_count == 3'd7) begin
                            estado <= DONE;
                        end else begin
                            bit_count <= bit_count + 3'd1; // Solo se incrementa el puntero
                        end
                    end else begin
                        tick_cnt <= tick_cnt + 1'b1;
                    end  
                end

                DONE: begin
                    done   <= 1'b1; // Señal de listo 
                    busy   <= 1'b0; // 0 la señal de ocupado
                    tx     <= 1'b1; // Devuelve la línea a nivel alto
                    estado <= IDLE; // Va al reposo otra vez
                end

                default: begin
                    estado <= IDLE;
                end
            endcase
        end
    end

endmodule

Lab00/codigos/punto 3/Ana/TBTrasA.v
`timescale 1ns/1ps

module TBTrasA;
    reg CLK = 0;
    reg rst = 0;
    reg start = 0;
    reg [7:0] data_in = 8'b0;
    wire busy;
    wire done;
    wire tx;

    
    TrasA uut (
        .CLK     (CLK),
        .rst   (rst),
        .start   (start),
        .data_in (data_in),
        .busy    (busy),
        .done    (done),
        .tx      (tx)
    );

    always begin
        #5 CLK = ~CLK;
    end

    initial begin

        $dumpfile("TBTrasA.vcd");
        $dumpvars(0, TBTrasA);

        // Monitoreo en consola
        $monitor("t=%0t ns | rst=%b | start=%b | data_in=%h | busy=%b | tx=%b | done=%b",
                 $time, rst, start, data_in, busy, tx, done);

        CLK     = 1'b0;
        rst     = 1'b1;
        start   = 1'b0;
        data_in = 8'b0;

        repeat (2) @(negedge CLK);
        rst = 1'b0;
        @(negedge CLK);

        // primera transmisión (0x05)
        data_in = 8'hA5;
        start   = 1'b1;
        @(negedge CLK);
        start   = 1'b0;

        wait(done); // Espera a que termine
        repeat (5) @(negedge CLK);

        // segunda transmisión (0xA3)
        rst     = 1'b1;
        data_in = 8'h3C;
        repeat (2) @(negedge CLK); 
        rst     = 1'b0;
        @(negedge CLK);

        start   = 1'b1;
        @(negedge CLK);
        start   = 1'b0;
        repeat (15) @(negedge CLK);

        
        rst = 1'b1; // Interrupción de la transmisión
        repeat (3) @(negedge CLK); 
        rst = 1'b0;               

        repeat (10) @(negedge CLK);
        $finish;
    end
endmodule

Lab00/codigos/punto 3/Ana/TBTrasA.vcd
$date
	Mon Sep 14 09:54:54 2026
$end
$version
	Icarus Verilog
$end
$timescale
	1ps
$end
$scope module TBTrasA $end
$var wire 1 ! tx $end
$var wire 1 " done $end
$var wire 1 # busy $end
$var reg 1 $ CLK $end
$var reg 8 % data_in [7:0] $end
$var reg 1 & rst $end
$var reg 1 ' start $end
$scope module uut $end
$var wire 1 $ CLK $end
$var wire 8 ( data_in [7:0] $end
$var wire 1 & rst $end
$var wire 1 ' start $end
$var parameter 32 ) CLKS_PER_BIT $end
$var parameter 2 * DONE $end
$var parameter 2 + IDLE $end
$var parameter 2 , LOAD $end
$var parameter 2 - TRANSMIT $end
$var reg 3 . bit_count [2:0] $end
$var reg 1 # busy $end
$var reg 1 " done $end
$var reg 2 / estado [1:0] $end
$var reg 8 0 shift_reg [7:0] $end
$var reg 3 1 tick_cnt [2:0] $end
$var reg 1 ! tx $end
$upscope $end
$upscope $end
$enddefinitions $end
$comment Show the parameter values. $end
$dumpall
b10 -
b1 ,
b0 +
b11 *
b1000 )
$end
#0
$dumpvars
b0 1
b0 0
b0 /
b0 .
b0 (
0'
1&
b0 %
0$
0#
0"
1!
$end
#5000
1$
#10000
0$
#15000
1$
#20000
0&
0$
#25000
1$
#30000
1'
b10100101 %
b10100101 (
0$
#35000
b1 /
1$
#40000
0'
0$
#45000
1#
b10100101 0
b10 /
1$
#50000
0$
#55000
b1 1
1$
#60000
0$
#65000
b10 1
1$
#70000
0$
#75000
b11 1
1$
#80000
0$
#85000
b100 1
1$
#90000
0$
#95000
b101 1
1$
#100000
0$
#105000
b110 1
1$
#110000
0$
#115000
b111 1
1$
#120000
0$
#125000
b1 .
b0 1
1$
#130000
0$
#135000
b1 1
0!
1$
#140000
0$
#145000
b10 1
1$
#150000
0$
#155000
b11 1
1$
#160000
0$
#165000
b100 1
1$
#170000
0$
#175000
b101 1
1$
#180000
0$
#185000
b110 1
1$
#190000
0$
#195000
b111 1
1$
#200000
0$
#205000
b10 .
b0 1
1$
#210000
0$
#215000
b1 1
1!
1$
#220000
0$
#225000
b10 1
1$
#230000
0$
#235000
b11 1
1$
#240000
0$
#245000
b100 1
1$
#250000
0$
#255000
b101 1
1$
#260000
0$
#265000
b110 1
1$
#270000
0$
#275000
b111 1
1$
#280000
0$
#285000
b11 .
b0 1
1$
#290000
0$
#295000
b1 1
0!
1$
#300000
0$
#305000
b10 1
1$
#310000
0$
#315000
b11 1
1$
#320000
0$
#325000
b100 1
1$
#330000
0$
#335000
b101 1
1$
#340000
0$
#345000
b110 1
1$
#350000
0$
#355000
b111 1
1$
#360000
0$
#365000
b100 .
b0 1
1$
#370000
0$
#375000
b1 1
1$
#380000
0$
#385000
b10 1
1$
#390000
0$
#395000
b11 1
1$
#400000
0$
#405000
b100 1
1$
#410000
0$
#415000
b101 1
1$
#420000
0$
#425000
b110 1
1$
#430000
0$
#435000
b111 1
1$
#440000
0$
#445000
b101 .
b0 1
1$
#450000
0$
#455000
b1 1
1!
1$
#460000
0$
#465000
b10 1
1$
#470000
0$
#475000
b11 1
1$
#480000
0$
#485000
b100 1
1$
#490000
0$
#495000
b101 1
1$
#500000
0$
#505000
b110 1
1$
#510000
0$
#515000
b111 1
1$
#520000
0$
#525000
b110 .
b0 1
1$
#530000
0$
#535000
b1 1
0!
1$
#540000
0$
#545000
b10 1
1$
#550000
0$
#555000
b11 1
1$
#560000
0$
#565000
b100 1
1$
#570000
0$
#575000
b101 1
1$
#580000
0$
#585000
b110 1
1$
#590000
0$
#595000
b111 1
1$
#600000
0$
#605000
b111 .
b0 1
1$
#610000
0$
#615000
b1 1
1!
1$
#620000
0$
#625000
b10 1
1$
#630000
0$
#635000
b11 1
1$
#640000
0$
#645000
b100 1
1$
#650000
0$
#655000
b101 1
1$
#660000
0$
#665000
b110 1
1$
#670000
0$
#675000
b111 1
1$
#680000
0$
#685000
b11 /
b0 1
1$
#690000
0$
#695000
b0 /
0#
1"
1$
#700000
0$
#705000
0"
1$
#710000
0$
#715000
1$
#720000
0$
#725000
1$
#730000
0$
#735000
1$
#740000
b0 0
b0 .
b111100 %
b111100 (
1&
0$
#745000
1$
#750000
0$
#755000
1$
#760000
0&
0$
#765000
1$
#770000
1'
0$
#775000
b1 /
1$
#780000
0'
0$
#785000
0!
1#
b111100 0
b10 /
1$
#790000
0$
#795000
b1 1
1$
#800000
0$
#805000
b10 1
1$
#810000
0$
#815000
b11 1
1$
#820000
0$
#825000
b100 1
1$
#830000
0$
#835000
b101 1
1$
#840000
0$
#845000
b110 1
1$
#850000
0$
#855000
b111 1
1$
#860000
0$
#865000
b1 .
b0 1
1$
#870000
0$
#875000
b1 1
1$
#880000
0$
#885000
b10 1
1$
#890000
0$
#895000
b11 1
1$
#900000
0$
#905000
b100 1
1$
#910000
0$
#915000
b101 1
1$
#920000
0$
#925000
b110 1
1$
#930000
b0 0
0#
1!
b0 1
b0 .
b0 /
1&
0$
#935000
1$
#940000
0$
#945000
1$
#950000
0$
#955000
1$
#960000
0&
0$
