Lab00/codigos/punto1/Top.v
module Top (
    input CLK,           // Reloj
    input reset,         // Reset
    output reg Verde,    // Salida luz verde encendida
    output reg Amarillo, // Salida luz amarilla encendida
    output reg Rojo      // Salida luz roja encendida

);
    //wire CLK;
    reg [1:0] estado; // Estado actual de la FSM (2 bits: 0,1,2 = Verde,Amarillo,Rojo) se actualiza en el bloque secuencial, memoria real (flip-flops) de la FSM
    reg [2:0] cuenta;  // Contador interno de ciclos dentro de cada estado, memoria
 
    /*
    DivCLK FSM1 (
        .OCLK (OCLK),
        .reset(reset),
        .CLK  (CLK)
    );*/
    // version Top, recibe CLK directamente en vez de generarlo internamente con DivCLK)
 
    // Bloque 1: logica secuencial (registros de estado), avanza 'estado' y 'cuenta' en cada flanco de CLK, reset

    always @(posedge CLK, posedge reset) begin
        if (reset) begin
            //reinicia el contador
            Verde <= 1'b0;
            Amarillo <= 1'b0;
            Rojo <= 1'b0;
            cuenta <= 3'd0;
        end
        else begin
            case (estado)
                // Estado Verde: dura 5 ciclos
                2'd0: if (cuenta == 3'd4) begin
                    estado <= 2'd1;      // pasa a Amarillo
                    cuenta <= 3'd0;
                end else cuenta <= cuenta + 3'd1;
 
                // Estado Amarillo: dura 2 ciclos
                2'd1: if (cuenta == 3'd1) begin
                    estado <= 2'd2;      // pasa a Rojo
                    cuenta <= 3'd0;
                end else cuenta <= cuenta + 3'd1;
 
                // Estado Rojo: dura 4 ciclos
                2'd2: if (cuenta == 3'd3) begin
                    estado <= 2'd0;      // vuelve a Verde
                    cuenta <= 3'd0;
                end else cuenta <= cuenta + 3'd1;
 
                // Estado invalido (2'd3, no deberia ocurrir): se fuerza a volver a Verde por seguridad.
                default: begin
                    estado <= 2'd0;
                    cuenta <= 3'd0;
                end
            endcase
        end
    end

    // Bloque 2: logica combinacional (decodificador de salidas) es el 'estado' actual en las luces fisicas encendidas
    always @(*) begin
        // Valores por defecto: todo apagado, evita latches y asegura que solo se encienda la luz correcta
        Verde = 1'b0;
        Amarillo = 1'b0;
        Rojo = 1'b0;
        case (estado)
            2'd0: Verde = 1'b1;
            2'd1: Amarillo = 1'b1;
            2'd2: Rojo = 1'b1;
            default: begin
                // Estado invalido: por seguridad se enciende Verde.
                Verde = 1'b1;
                Amarillo = 1'b0;
                Rojo = 1'b0;
            end
        endcase
    end
endmodule

Lab00/codigos/punto1/TBtop.v
`timescale 1ns/1ps   // Unidad de tiempo = 1ns, precision = 1ps
 
module TBtop;
    // CLK y reset son 'reg' porque el testbench los controla "a mano", en un testbench, las entradas del DUT (Device Under Test) siempre deben declararse como reg
    reg CLK = 0;
    reg reset = 0;

    wire Verde;
    wire Amarillo;
    wire Rojo;
 
    // Instancia del modulo a probar (DUT), conectando cada puerto

    Top uut (
        .CLK     (CLK),
        .reset   (reset),
        .Verde   (Verde),
        .Amarillo(Amarillo),
        .Rojo    (Rojo)
    );
 
    // Generador de reloj: invierte CLK cada 5ns -> periodo de 10ns (frecuencia de 100 MHz en la escala de tiempo definida arriba).
    always begin
        #5 CLK = ~CLK;
    end
 
    // Secuencia de estimulos de la simulacion.
    initial begin
        // Configura el volcado de señales para poder verlas despues en un visor de ondas
        $dumpfile("TBtop.vcd");   // archivo de salida
        $dumpvars(0, TBtop);      // graba todas las señales de este modulo (nivel 0 = recursivo)
 
        // --- Primer ciclo de reset ---
        #5;
        reset = 1'b1;   // activa reset
 
        #5;
        reset = 0;      // libera reset, la FSM empieza a correr
 
        // Deja correr la FSM libremente 500ns para observar su comportamiento normal (cambios de estado del semaforo)
        #500;
 
        // --- Segundo ciclo de reset (prueba que se puede resetear
        //     de nuevo en cualquier momento, no solo al inicio) ---
        reset = 1'b1;
 
        #5
        reset = 0;
 
        // Deja correr otros 500ns tras el segundo reset
        #500;
 
        $finish;   // termina la simulacion
    end
endmodule

Lab00/codigos/punto1/TBtop.vcd
$date
	Sun Sep 06 16:00:55 2026
$end
$version
	Icarus Verilog
$end
$timescale
	1ps
$end
$scope module TBtop $end
$var wire 1 ! Verde $end
$var wire 1 " Rojo $end
$var wire 1 # Amarillo $end
$var reg 1 $ CLK $end
$var reg 1 % reset $end
$scope module uut $end
$var wire 1 $ CLK $end
$var wire 1 % reset $end
$var reg 1 # Amarillo $end
$var reg 1 " Rojo $end
$var reg 1 ! Verde $end
$var reg 3 & cuenta [2:0] $end
$var reg 2 ' estado [1:0] $end
$upscope $end
$upscope $end
$enddefinitions $end
$comment Show the parameter values. $end
$dumpall
$end
#0
$dumpvars
bx '
bx &
0%
0$
x#
x"
x!
$end
#5000
b0 &
0"
0#
0!
1%
1$
#10000
0%
0$
#15000
1!
b0 '
1$
#20000
0$
#25000
b1 &
1$
#30000
0$
#35000
b10 &
1$
#40000
0$
#45000
b11 &
1$
#50000
0$
#55000
b100 &
1$
#60000
0$
#65000
1#
0!
b0 &
b1 '
1$
#70000
0$
#75000
b1 &
1$
#80000
0$
#85000
1"
0#
b0 &
b10 '
1$
#90000
0$
#95000
b1 &
1$
#100000
0$
#105000
b10 &
1$
#110000
0$
#115000
b11 &
1$
#120000
0$
#125000
1!
0"
b0 &
b0 '
1$
#130000
0$
#135000
b1 &
1$
#140000
0$
#145000
b10 &
1$
#150000
0$
#155000
b11 &
1$
#160000
0$
#165000
b100 &
1$
#170000
0$
#175000
1#
0!
b0 &
b1 '
1$
#180000
0$
#185000
b1 &
1$
#190000
0$
#195000
1"
0#
b0 &
b10 '
1$
#200000
0$
#205000
b1 &
1$
#210000
0$
#215000
b10 &
1$
#220000
0$
#225000
b11 &
1$
#230000
0$
#235000
1!
0"
b0 &
b0 '
1$
#240000
0$
#245000
b1 &
1$
#250000
0$
#255000
b10 &
1$
#260000
0$
#265000
b11 &
1$
#270000
0$
#275000
b100 &
1$
#280000
0$
#285000
1#
0!
b0 &
b1 '
1$
#290000
0$
#295000
b1 &
1$
#300000
0$
#305000
1"
0#
b0 &
b10 '
1$
#310000
0$
#315000
b1 &
1$
#320000
0$
#325000
b10 &
1$
#330000
0$
#335000
b11 &
1$
#340000
0$
#345000
1!
0"
b0 &
b0 '
1$
#350000
0$
#355000
b1 &
1$
#360000
0$
#365000
b10 &
1$
#370000
0$
#375000
b11 &
1$
#380000
0$
#385000
b100 &
1$
#390000
0$
#395000
1#
0!
b0 &
b1 '
1$
#400000
0$
#405000
b1 &
1$
#410000
0$
#415000
1"
0#
b0 &
b10 '
1$
#420000
0$
#425000
b1 &
1$
#430000
0$
#435000
b10 &
1$
#440000
0$
#445000
b11 &
1$
#450000
0$
#455000
1!
0"
b0 &
b0 '
1$
#460000
0$
#465000
b1 &
1$
#470000
0$
#475000
b10 &
1$
#480000
0$
#485000
b11 &
1$
#490000
0$
#495000
b100 &
1$
#500000
0$
#505000
1#
0!
b0 &
b1 '
1$
#510000
0#
0$
1%
#515000
b1 &
1$
0%
#520000
0$
#525000
1"
b0 &
b10 '
1$
#530000
0$
#535000
b1 &
1$
#540000
0$
#545000
b10 &
1$
#550000
0$
#555000
b11 &
1$
#560000
0$
#565000
1!
0"
b0 &
b0 '
1$
#570000
0$
#575000
b1 &
1$
#580000
0$
#585000
b10 &
1$
#590000
0$
#595000
b11 &
1$
#600000
0$
#605000
b100 &
1$
#610000
0$
#615000
1#
0!
b0 &
b1 '
1$
#620000
0$
#625000
b1 &
1$
#630000
0$
#635000
1"
0#
b0 &
b10 '
1$
#640000
0$
#645000
b1 &
1$
#650000
0$
#655000
b10 &
1$
#660000
0$
#665000
b11 &
1$
#670000
0$
#675000
1!
0"
b0 &
b0 '
1$
#680000
0$
#685000
b1 &
1$
#690000
0$
#695000
b10 &
1$
#700000
0$
#705000
b11 &
1$
#710000
0$
#715000
b100 &
1$
#720000
0$
#725000
1#
0!
b0 &
b1 '
1$
#730000
0$
#735000
b1 &
1$
#740000
0$
#745000
1"
0#
b0 &
b10 '
1$
#750000
0$
#755000
b1 &
1$
#760000
0$
#765000
b10 &
1$
#770000
0$
#775000
b11 &
1$
#780000
0$
#785000
1!
0"
b0 &
b0 '
1$
#790000
0$
#795000
b1 &
1$
#800000
0$
#805000
b10 &
1$
#810000
0$
#815000
b11 &
1$
#820000
0$
#825000
b100 &
1$
#830000
0$
#835000
1#
0!
b0 &
b1 '
1$
#840000
0$
#845000
b1 &
1$
#850000
0$
#855000
1"
0#
b0 &
b10 '
1$
#860000
0$
#865000
b1 &
1$
#870000
0$
#875000
b10 &
1$
#880000
0$
#885000
b11 &
1$
#890000
0$
#895000
1!
0"
b0 &
b0 '
1$
#900000
0$
#905000
b1 &
1$
#910000
0$
#915000
b10 &
1$
#920000
0$
#925000
b11 &
1$
#930000
0$
#935000
b100 &
1$
#940000
0$
#945000
1#
0!
b0 &
b1 '
1$
#950000
0$
#955000
b1 &
1$
#960000
0$
#965000
1"
0#
b0 &
b10 '
1$
#970000
0$
#975000
b1 &
1$
#980000
0$
#985000
b10 &
1$
#990000
0$
#995000
b11 &
1$
#1000000
0$
#1005000
1!
0"
b0 &
b0 '
1$
#1010000
0$
#1015000
b1 &
1$
