Lab00/codigos/punto 3/Mar/transmisor.v

// Transmisor Serial 
module serial_tx #(
    parameter CLKS_PER_BIT = 8 
)(
    input  wire       clk,
    input  wire       rst,
    input  wire       start,
    input  wire [7:0] data_in,
    output reg        tx,
    output reg        busy,
    output reg        done
);

    // Codificacion de los 5 estados
    localparam IDLE       = 3'd0,
               LOAD       = 3'd1,
               BIT_HOLD   = 3'd2,
               SHIFT_NEXT = 3'd3,
               DONE_ST    = 3'd4;

    reg [2:0] state, next_state;

    reg [7:0] shift_reg;
    reg [2:0] bit_count; 
    reg [$clog2(CLKS_PER_BIT)-1:0] tick_cnt;

    // FSM: Memoria de estado
    always @(posedge clk or posedge rst) begin
        if (rst) state <= IDLE;
        else     state <= next_state;
    end

    //  FSM: Logica combinacional de proximo estado 
    always @(*) begin
        case (state)
            IDLE:       next_state = start ? LOAD : IDLE;
            LOAD:       next_state = BIT_HOLD;
            
            // Se queda en BIT_HOLD hasta que el tiempo del bit termine
            BIT_HOLD:   next_state = (tick_cnt == CLKS_PER_BIT - 1) ? SHIFT_NEXT : BIT_HOLD;
            
            // Decide si pasa al siguiente bit o si ya termino los 8
            SHIFT_NEXT: next_state = (bit_count == 3'd7) ? DONE_ST : BIT_HOLD;
            
            DONE_ST:    next_state = IDLE;
            default:    next_state = IDLE;
        endcase
    end

    // Datapath: Registros y temporizacion 
    always @(posedge clk or posedge rst) begin
        if (rst) begin
            tx        <= 1'b1;
            busy      <= 1'b0;
            done      <= 1'b0;
            shift_reg <= 8'd0;
            bit_count <= 3'd0;
            tick_cnt  <= 0;
        end else begin
            case (state)
                IDLE: begin
                    tx   <= 1'b1;
                    busy <= 1'b0;
                    done <= 1'b0;
                end
                LOAD: begin
                    shift_reg <= data_in;
                    bit_count <= 3'd0;
                    tick_cnt  <= 0;
                    busy      <= 1'b1;
                    tx        <= 1'b1;
                    done      <= 1'b0;
                end
                BIT_HOLD: begin
                    tx   <= shift_reg[0]; // Mantiene la linea con el bit actual
                    busy <= 1'b1;
                    done <= 1'b0;
                    // Incrementa el temporizador si aun no termina
                    if (tick_cnt < CLKS_PER_BIT - 1) begin
                        tick_cnt <= tick_cnt + 1'b1;
                    end
                end
                SHIFT_NEXT: begin
                    busy <= 1'b1;
                    tick_cnt <= 0; // Reinicia el temporizador para el nuevo bit
                    if (bit_count < 3'd7) begin
                        shift_reg <= {1'b0, shift_reg[7:1]}; // Desplaza
                        bit_count <= bit_count + 1'b1;       // Cuenta el nuevo bit
                    end
                end
                DONE_ST: begin
                    done <= 1'b1;
                    busy <= 1'b0;
                    tx   <= 1'b1; 
                end
            endcase
        end
    end
endmodule

Lab00/codigos/punto 3/Mar/main3.v
`timescale 1ns / 1ps

module tb_serial_tx;

    reg clk;
    reg rst;
    reg start;
    reg [7:0] data_in;
    
    wire tx;
    wire busy;
    wire done;

    // Instancia del módulo
    serial_tx #(
        .CLKS_PER_BIT(8) // Usamos 8 ciclos por bit para la simulación
    ) dut (
        .clk(clk),
        .rst(rst),
        .start(start),
        .data_in(data_in),
        .tx(tx),
        .busy(busy),
        .done(done)
    );

    // Generador de reloj (Periodo de 10ns)
    initial clk = 0;
    always #5 clk = ~clk;

    initial begin
        // Configuración para GTKWave
        $dumpfile("wave.vcd");
        $dumpvars(0, tb_serial_tx);

        // Inicialización y Reset
        rst = 1;
        start = 0;
        data_in = 8'h00;
        #20;
        rst = 0;
        #20;

        // ---- Transmisión 1: 8'hA5 (10100101) ----
        // Al enviar LSB primero, tx debería mostrar: 1, 0, 1, 0, 0, 1, 0, 1
        data_in = 8'hA5;
        start = 1;      // Pulso de 1 ciclo
        #10 start = 0;
        
        // Espera a que termine la transmisión
        wait(done == 1);
        #40;

        // ---- Transmisión 2: 8'h3C (00111100) ----
        // LSB primero: 0, 0, 1, 1, 1, 1, 0, 0
        data_in = 8'h3C;
        start = 1;
        #10 start = 0;

        wait(done == 1);
        #40;

        $display("Simulación completada con éxito.");
        $finish;
    end
endmodule

Lab00/codigos/punto 3/Mar/wave.vcd
$date
	Sat Sep 19 18:01:01 2026
$end
$version
	Icarus Verilog
$end
$timescale
	1ps
$end
$scope module tb_serial_tx $end
$var wire 1 ! tx $end
$var wire 1 " done $end
$var wire 1 # busy $end
$var reg 1 $ clk $end
$var reg 8 % data_in [7:0] $end
$var reg 1 & rst $end
$var reg 1 ' start $end
$scope module dut $end
$var wire 1 $ clk $end
$var wire 8 ( data_in [7:0] $end
$var wire 1 & rst $end
$var wire 1 ' start $end
$var parameter 3 ) BIT_HOLD $end
$var parameter 32 * CLKS_PER_BIT $end
$var parameter 3 + DONE_ST $end
$var parameter 3 , IDLE $end
$var parameter 3 - LOAD $end
$var parameter 3 . SHIFT_NEXT $end
$var reg 3 / bit_count [2:0] $end
$var reg 1 # busy $end
$var reg 1 " done $end
$var reg 3 0 next_state [2:0] $end
$var reg 8 1 shift_reg [7:0] $end
$var reg 3 2 state [2:0] $end
$var reg 3 3 tick_cnt [2:0] $end
$var reg 1 ! tx $end
$upscope $end
$upscope $end
$enddefinitions $end
$comment Show the parameter values. $end
$dumpall
b11 .
b1 -
b0 ,
b100 +
b1000 *
b10 )
$end
#0
$dumpvars
b0 3
b0 2
b0 1
b0 0
b0 /
b0 (
0'
1&
b0 %
0$
0#
0"
1!
$end
#5000
1$
#10000
0$
#15000
1$
#20000
0$
0&
#25000
1$
#30000
0$
#35000
1$
#40000
b1 0
0$
1'
b10100101 %
b10100101 (
#45000
b10 0
b1 2
1$
#50000
0$
0'
#55000
b10 2
1#
b10100101 1
1$
#60000
0$
#65000
b1 3
1$
#70000
0$
#75000
b10 3
1$
#80000
0$
#85000
b11 3
1$
#90000
0$
#95000
b100 3
1$
#100000
0$
#105000
b101 3
1$
#110000
0$
#115000
b110 3
1$
#120000
0$
#125000
b11 0
b111 3
1$
#130000
0$
#135000
b10 0
b11 2
1$
#140000
0$
#145000
b1 /
b1010010 1
b0 3
b10 2
1$
#150000
0$
#155000
b1 3
0!
1$
#160000
0$
#165000
b10 3
1$
#170000
0$
#175000
b11 3
1$
#180000
0$
#185000
b100 3
1$
#190000
0$
#195000
b101 3
1$
#200000
0$
#205000
b110 3
1$
#210000
0$
#215000
b11 0
b111 3
1$
#220000
0$
#225000
b10 0
b11 2
1$
#230000
0$
#235000
b10 2
b10 /
b101001 1
b0 3
1$
#240000
0$
#245000
b1 3
1!
1$
#250000
0$
#255000
b10 3
1$
#260000
0$
#265000
b11 3
1$
#270000
0$
#275000
b100 3
1$
#280000
0$
#285000
b101 3
1$
#290000
0$
#295000
b110 3
1$
#300000
0$
#305000
b11 0
b111 3
1$
#310000
0$
#315000
b10 0
b11 2
1$
#320000
0$
#325000
b11 /
b10100 1
b0 3
b10 2
1$
#330000
0$
#335000
b1 3
0!
1$
#340000
0$
#345000
b10 3
1$
#350000
0$
#355000
b11 3
1$
#360000
0$
#365000
b100 3
1$
#370000
0$
#375000
b101 3
1$
#380000
0$
#385000
b110 3
1$
#390000
0$
#395000
b11 0
b111 3
1$
#400000
0$
#405000
b10 0
b11 2
1$
#410000
0$
#415000
b10 2
b100 /
b1010 1
b0 3
1$
#420000
0$
#425000
b1 3
1$
#430000
0$
#435000
b10 3
1$
#440000
0$
#445000
b11 3
1$
#450000
0$
#455000
b100 3
1$
#460000
0$
#465000
b101 3
1$
#470000
0$
#475000
b110 3
1$
#480000
0$
#485000
b11 0
b111 3
1$
#490000
0$
#495000
b10 0
b11 2
1$
#500000
0$
#505000
b101 /
b101 1
b0 3
b10 2
1$
#510000
0$
#515000
b1 3
1!
1$
#520000
0$
#525000
b10 3
1$
#530000
0$
#535000
b11 3
1$
#540000
0$
#545000
b100 3
1$
#550000
0$
#555000
b101 3
1$
#560000
0$
#565000
b110 3
1$
#570000
0$
#575000
b11 0
b111 3
1$
#580000
0$
#585000
b10 0
b11 2
1$
#590000
0$
#595000
b10 2
b110 /
b10 1
b0 3
1$
#600000
0$
#605000
b1 3
0!
1$
#610000
0$
#615000
b10 3
1$
#620000
0$
#625000
b11 3
1$
#630000
0$
#635000
b100 3
1$
#640000
0$
#645000
b101 3
1$
#650000
0$
#655000
b110 3
1$
#660000
0$
#665000
b11 0
b111 3
1$
#670000
0$
#675000
b10 0
b11 2
1$
#680000
0$
#685000
b111 /
b1 1
b0 3
b10 2
1$
#690000
0$
#695000
b1 3
1!
1$
#700000
0$
#705000
b10 3
1$
#710000
0$
#715000
b11 3
1$
#720000
0$
#725000
b100 3
1$
#730000
0$
#735000
b101 3
1$
#740000
0$
#745000
b110 3
1$
#750000
0$
#755000
b11 0
b111 3
1$
#760000
0$
#765000
b100 0
b11 2
1$
#770000
0$
#775000
b0 0
b100 2
b0 3
1$
#780000
0$
#785000
0#
1"
b0 2
1$
#790000
0$
#795000
0"
1$
#800000
0$
#805000
1$
#810000
0$
#815000
1$
#820000
0$
#825000
b1 2
b10 0
1$
1'
b111100 %
b111100 (
#830000
0$
#835000
b10 2
1#
b0 /
b111100 1
1$
0'
#840000
0$
#845000
b1 3
0!
1$
#850000
0$
#855000
b10 3
1$
#860000
0$
#865000
b11 3
1$
#870000
0$
#875000
b100 3
1$
#880000
0$
#885000
b101 3
1$
#890000
0$
#895000
b110 3
1$
#900000
0$
#905000
b11 0
b111 3
1$
#910000
0$
#915000
b10 0
b11 2
1$
#920000
0$
#925000
b1 /
b11110 1
b0 3
b10 2
1$
#930000
0$
#935000
b1 3
1$
#940000
0$
#945000
b10 3
1$
#950000
0$
#955000
b11 3
1$
#960000
0$
#965000
b100 3
1$
#970000
0$
#975000
b101 3
1$
#980000
0$
#985000
b110 3
1$
#990000
0$
#995000
b11 0
b111 3
1$
#1000000
0$
#1005000
b10 0
b11 2
1$
#1010000
0$
#1015000
b10 2
b10 /
b1111 1
b0 3
1$
#1020000
0$
#1025000
b1 3
1!
1$
#1030000
0$
#1035000
b10 3
1$
#1040000
0$
#1045000
b11 3
1$
#1050000
0$
#1055000
b100 3
1$
#1060000
0$
#1065000
b101 3
1$
#1070000
0$
#1075000
b110 3
1$
#1080000
0$
#1085000
b11 0
b111 3
1$
#1090000
0$
#1095000
b10 0
b11 2
1$
#1100000
0$
#1105000
b11 /
b111 1
b0 3
b10 2
1$
#1110000
0$
#1115000
b1 3
1$
#1120000
0$
#1125000
b10 3
1$
#1130000
0$
#1135000
b11 3
1$
#1140000
0$
#1145000
b100 3
1$
#1150000
0$
#1155000
b101 3
1$
#1160000
0$
#1165000
b110 3
1$
#1170000
0$
#1175000
b11 0
b111 3
1$
#1180000
0$
#1185000
b10 0
b11 2
1$
#1190000
0$
#1195000
b10 2
b100 /
b11 1
b0 3
1$
#1200000
0$
#1205000
b1 3
1$
#1210000
0$
#1215000
b10 3
1$
#1220000
0$
#1225000
b11 3
1$
#1230000
0$
#1235000
b100 3
1$
#1240000
0$
#1245000
b101 3
1$
#1250000
0$
#1255000
b110 3
1$
#1260000
0$
#1265000
b11 0
b111 3
1$
#1270000
0$
#1275000
b10 0
b11 2
1$
#1280000
0$
#1285000
b101 /
b1 1
b0 3
b10 2
1$
#1290000
0$
#1295000
b1 3
1$
#1300000
0$
#1305000
b10 3
1$
#1310000
0$
#1315000
b11 3
1$
#1320000
0$
#1325000
b100 3
1$
#1330000
0$
#1335000
b101 3
1$
#1340000
0$
#1345000
b110 3
1$
#1350000
0$
#1355000
b11 0
b111 3
1$
#1360000
0$
#1365000
b10 0
b11 2
1$
#1370000
0$
#1375000
b10 2
b110 /
b0 1
b0 3
1$
#1380000
0$
#1385000
b1 3
0!
1$
#1390000
0$
#1395000
b10 3
1$
#1400000
0$
#1405000
b11 3
1$
#1410000
0$
#1415000
b100 3
1$
#1420000
0$
#1425000
b101 3
1$
#1430000
0$
#1435000
b110 3
1$
#1440000
0$
#1445000
b11 0
b111 3
1$
#1450000
0$
#1455000
b10 0
b11 2
1$
#1460000
0$
#1465000
b111 /
b0 3
b10 2
1$
#1470000
0$
#1475000
b1 3
1$
#1480000
0$
#1485000
b10 3
1$
#1490000
0$
#1495000
b11 3
1$
#1500000
0$
#1505000
b100 3
1$
#1510000
0$
#1515000
b101 3
1$
#1520000
0$
#1525000
b110 3
1$
#1530000
0$
#1535000
b11 0
b111 3
1$
#1540000
0$
#1545000
b100 0
b11 2
1$
#1550000
0$
#1555000
b0 0
b100 2
b0 3
1$
#1560000
0$
#1565000
1!
0#
1"
b0 2
1$
#1570000
0$
#1575000
0"
1$
