Lab02/códigos/ALU2.V
// Módulo ALU2: Unidad Aritmético Lógica de 4 bits controlada por una Máquina de Estados Finitos (FSM)
module ALU2 (
    input clk,          // Reloj del sistema
    input [3:0] sw,     // Interruptores de entrada (para ingresar operandos A y B)
    input [3:0] btn,    // Botones de control (transición de estados y cambio de modo)
    output reg [3:0] led, // Salida de LEDs (muestra switches o resultado de la operación)
    output reg [2:0] rgb  // Salida para LED RGB (indica la operación actual)
);
    // Registros internos de la máquina de estados y operandos
    reg [2:0] estado; // Estado actual de la FSM (0 a 5)
    reg [3:0] A;      // Registro para el primer operando
    reg [3:0] B;      // Registro para el segundo operando
    reg [1:0] modo;   // Selector de operación ALU (0: Suma, 1: Resta, 2: AND, 3: OR)

    // Lógica secuencial (FSM): Captura de operandos, cambio de modo y transición de estados
    always @(posedge clk) begin
        case (estado)
            // Estado 0: Espera la pulsación de btn[0] para capturar el operando A desde los switches
            3'd0: if (btn[0]) begin
                A <= sw;
                estado <= 3'd1;
            end
            
            // Estado 1: Anti-rebote/espera a que se libere btn[0]
            3'd1: if (!btn[0]) estado <= 3'd2;
            
            // Estado 2: Espera la pulsación de btn[1] para capturar el operando B desde los switches
            3'd2: if (btn[1]) begin
                B <= sw;
                estado <= 3'd3;
            end
            
            // Estado 3: Anti-rebote/espera a que se libere btn[1]
            3'd3: if (!btn[1]) estado <= 3'd4;
            
            // Estado 4: Modo de ejecución / Selección de operación
            // - Presionar btn[0] o btn[1] avanza al estado 5 para reiniciar el flujo.
            // - Presionar btn[2] conmuta el bit inferior de modo (modo[0]).
            // - Presionar btn[3] conmuta el bit superior de modo (modo[1]).
            3'd4: if (btn[0] | btn[1]) estado <= 3'd5;
                else if (btn[2]) modo[0] <= ~modo[0];
                else if (btn[3]) modo[1] <= ~modo[1];
            
            // Estado 5: Espera a que se liberen btn[0] y btn[1] para reiniciar la FSM al estado 0
            3'd5: if (!(btn[0] | btn[1])) estado <= 3'd0;
            
            // Estado por defecto: Reinicia las señales si ocurre un estado inválido
            default: begin
                estado <= 0;
                A <= 0;
                B <= 0;
                modo <= 0;
            end
        endcase
    end

    // Lógica combinacional: Salidas para los LEDs y el LED RGB según el estado y el modo
    always @(*) begin
        rgb = 0; // Valor por defecto del RGB
        case (estado)
            // En los estados 0 a 3, los LEDs reflejan directamente la posición actual de los switches
            3'd0, 3'd1, 3'd2, 3'd3: led = sw;
            
            // En los estados 4 y 5, los LEDs muestran el resultado de la ALU según 'modo'
            3'd4, 3'd5: begin
                case (modo)
                    2'd0: begin // Operación: Suma (A + B)
                        led = A+B;
                        rgb = 3'b010; // Color RGB para Suma
                    end
                    2'd1: begin // Operación: Resta (A - B)
                        led = A-B;
                        rgb = 3'b001; // Color RGB para Resta
                    end
                    2'd2: begin // Operación: AND bit a bit (A & B)
                        led = A&B;
                        rgb = 3'b100; // Color RGB para AND
                    end
                    2'd3: begin // Operación: OR bit a bit (A | B)
                        led = A|B;
                        rgb = 3'b111; // Color RGB para OR
                    end
                    default: begin
                        led = A+B;
                        rgb = 3'b010;
                    end 
                endcase
            end
            
            // Estado por defecto para la lógica combinacional de salida
            default: begin
                led = 0;
                rgb = 0;
            end
        endcase
    end
endmodule

Lab02/TBALU2.v
`timescale 1ns/1ps

module TBALU2;
    // Entradas al módulo (reg para controlarlas en el initial)
    reg clk = 0;
    reg [3:0] sw = 0;
    reg [3:0] btn = 0;

    // Salidas del módulo (wire para leer la respuesta)
    wire [3:0] led;
    wire [2:0] rgb;

    // Instanciación de la ALU (UUT)
    ALU2 uut (
        .clk (clk),
        .sw  (sw),
        .btn (btn),
        .led (led),
        .rgb (rgb)
    );

    // Generador de reloj: período de 10ns (50MHz)
    always #5 clk = ~clk;

    initial begin
        $dumpfile("TBALU2.vcd");
        $dumpvars(0, TBALU2);

        // Inicialización
        sw  = 4'b0000;
        btn = 4'b0000;
        #10;

        // Operandos
        // Cargar A = 3
        sw = 4'b0011;
        btn = 4'b0001; // btn[0]
        #10;
        btn = 4'b0000;
        #10;

        // Cargar B = 5
        sw = 4'b0101;
        btn = 4'b0010; // btn[1]
        #10;
        btn = 4'b0000;
        #10; // Estado 4
        
        // MODO 00 (Suma: 3 + 5 = 8)
        #20;

        // MODO 01 (Resta: 3 - 5 = E)
        btn = 4'b0100; // Activa btn[2]
        #10;
        btn = 4'b0000;
        #20;

        // MODO 11 (OR: 3 OR 5 = 7)
        // Correccion de error: Se presiona btn[3] inmediatamente en la misma ventana de tiempo
        btn = 4'b1000; // Activa btn[3]
        #10;
        btn = 4'b0000;
        #20;
        // --- 4. MODO 10 (AND) ---
        // Pulsar btn[2] para conmutar modo[0] de 1 a 0 (11 -> 10)
        btn = 4'b0100; // Activa btn[2]
        #10;
        btn = 4'b0000;
        #20;

        $finish;
        $finish;
    end
endmodule

Lab02/códigos/TBALU2.vcd
$date
	Thu Oct 08 16:27:31 2026
$end
$version
	Icarus Verilog
$end
$timescale
	1ps
$end
$scope module TBALU2 $end
$var wire 3 ! rgb [2:0] $end
$var wire 4 " led [3:0] $end
$var reg 4 # btn [3:0] $end
$var reg 1 $ clk $end
$var reg 4 % sw [3:0] $end
$scope module uut $end
$var wire 4 & btn [3:0] $end
$var wire 1 $ clk $end
$var wire 4 ' sw [3:0] $end
$var reg 4 ( A [3:0] $end
$var reg 4 ) B [3:0] $end
$var reg 3 * estado [2:0] $end
$var reg 4 + led [3:0] $end
$var reg 2 , modo [1:0] $end
$var reg 3 - rgb [2:0] $end
$upscope $end
$upscope $end
$enddefinitions $end
$comment Show the parameter values. $end
$dumpall
$end
#0
$dumpvars
b0 -
bx ,
b0 +
bx *
bx )
bx (
b0 '
b0 &
b0 %
0$
b0 #
b0 "
b0 !
$end
#5000
b0 ,
b0 )
b0 (
b0 *
1$
#10000
b11 "
b11 +
0$
b1 #
b1 &
b11 %
b11 '
#15000
b1 *
b11 (
1$
#20000
0$
b0 #
b0 &
#25000
b10 *
1$
#30000
b101 "
b101 +
0$
b10 #
b10 &
b101 %
b101 '
#35000
b11 *
b101 )
1$
#40000
0$
b0 #
b0 &
#45000
b10 !
b10 -
b1000 "
b1000 +
b100 *
1$
#50000
0$
#55000
1$
#60000
0$
#65000
1$
#70000
0$
b100 #
b100 &
#75000
b1110 "
b1110 +
b1 !
b1 -
b1 ,
1$
#80000
0$
b0 #
b0 &
#85000
1$
#90000
0$
#95000
1$
#100000
0$
b1000 #
b1000 &
#105000
b111 "
b111 +
b111 !
b111 -
b11 ,
1$
#110000
0$
b0 #
b0 &
#115000
1$
#120000
0$
#125000
1$
#130000
0$
b100 #
b100 &
#135000
b1 "
b1 +
b100 !
b100 -
b10 ,
1$
#140000
0$
b0 #
b0 &
