Lab00/codigos/punto1/Nico/Top.v
module Top (
    input CLK,
    input reset,
    output reg Verde,
    output reg Amarillo,
    output reg Rojo
);
    //wire CLK;
    reg [1:0] estado;
    reg [2:0] cuenta;

    always @(posedge CLK, posedge reset) begin
        if (reset) begin
            estado <= 2'd0;
            cuenta <= 3'd0;
        end
        else begin
            case (estado)
                2'd0: if (cuenta == 3'd4) begin
                    estado <= 2'd1;
                    cuenta <= 3'd0;
                end else cuenta <= cuenta + 3'd1;
                2'd1: if (cuenta == 3'd1) begin
                    estado <= 2'd2;
                    cuenta <= 3'd0;
                end else cuenta <= cuenta + 3'd1;
                2'd2: if (cuenta == 3'd3) begin
                    estado <= 2'd3;
                    cuenta <= 3'd0;
                end else cuenta <= cuenta + 3'd1;
                2'd3: if (cuenta == 3'd1) begin
                    estado <= 2'd0;
                    cuenta <= 3'd0;
                end else cuenta <= cuenta + 3'd1;
                default: begin
                    estado <= 2'd0;
                    cuenta <= 3'd0;
                end
            endcase
        end
    end

    always @(*) begin
        Verde = 1'b0;
        Amarillo = 1'b0;
        Rojo = 1'b0;
        case (estado)
            2'd0: Verde = 1'b1;
            2'd1: Amarillo = 1'b1;
            2'd2: Rojo = 1'b1;
            3'd3: Amarillo = 1'b1;
            default: begin
                Verde = 1'b1;
                Amarillo = 1'b0;
                Rojo = 1'b0;
            end
        endcase
    end
endmodule

Lab00/codigos/punto1/Nico/TBtop.v
`timescale 1ns/1ps

module TBtop;
    reg CLK = 0;
    reg reset = 0;

    wire Verde;
    wire Amarillo;
    wire Rojo;
    
    Top uut (
        .CLK     (CLK),
        .reset   (reset),
        .Verde   (Verde),
        .Amarillo(Amarillo),
        .Rojo    (Rojo)
    );

    always begin
        #5 CLK = ~CLK;
    end

    initial begin
        $dumpfile("TBtop.vcd");
        $dumpvars(0, TBtop);

        #5;
        reset = 1'b1;

        #5;
        reset = 0;

        #500;
        reset = 1'b1;

        #5
        reset = 0;

        #500;

        $finish;
    end
endmodule

Lab00/codigos/punto1/Nico/TBtop.vcd
$date
	Sun Sep 13 10:21:38 2026
$end
$version
	Icarus Verilog
$end
$timescale
	1ps
$end
$scope module TBtop $end
$var wire 1 ! Verde $end
$var wire 1 " Rojo $end
$var wire 1 # Amarillo $end
$var reg 1 $ CLK $end
$var reg 1 % reset $end
$scope module uut $end
$var wire 1 $ CLK $end
$var wire 1 % reset $end
$var reg 1 # Amarillo $end
$var reg 1 " Rojo $end
$var reg 1 ! Verde $end
$var reg 3 & cuenta [2:0] $end
$var reg 2 ' estado [1:0] $end
$upscope $end
$upscope $end
$enddefinitions $end
$comment Show the parameter values. $end
$dumpall
$end
#0
$dumpvars
bx '
bx &
0%
0$
x#
x"
x!
$end
#5000
0"
0#
1!
b0 &
b0 '
1%
1$
#10000
0%
0$
#15000
b1 &
1$
#20000
0$
#25000
b10 &
1$
#30000
0$
#35000
b11 &
1$
#40000
0$
#45000
b100 &
1$
#50000
0$
#55000
1#
0!
b0 &
b1 '
1$
#60000
0$
#65000
b1 &
1$
#70000
0$
#75000
1"
0#
b0 &
b10 '
1$
#80000
0$
#85000
b1 &
1$
#90000
0$
#95000
b10 &
1$
#100000
0$
#105000
b11 &
1$
#110000
0$
#115000
1#
0"
b0 &
b11 '
1$
#120000
0$
#125000
b1 &
1$
#130000
0$
#135000
1!
0#
b0 &
b0 '
1$
#140000
0$
#145000
b1 &
1$
#150000
0$
#155000
b10 &
1$
#160000
0$
#165000
b11 &
1$
#170000
0$
#175000
b100 &
1$
#180000
0$
#185000
1#
0!
b0 &
b1 '
1$
#190000
0$
#195000
b1 &
1$
#200000
0$
#205000
1"
0#
b0 &
b10 '
1$
#210000
0$
#215000
b1 &
1$
#220000
0$
#225000
b10 &
1$
#230000
0$
#235000
b11 &
1$
#240000
0$
#245000
1#
0"
b0 &
b11 '
1$
#250000
0$
#255000
b1 &
1$
#260000
0$
#265000
1!
0#
b0 &
b0 '
1$
#270000
0$
#275000
b1 &
1$
#280000
0$
#285000
b10 &
1$
#290000
0$
#295000
b11 &
1$
#300000
0$
#305000
b100 &
1$
#310000
0$
#315000
1#
0!
b0 &
b1 '
1$
#320000
0$
#325000
b1 &
1$
#330000
0$
#335000
1"
0#
b0 &
b10 '
1$
#340000
0$
#345000
b1 &
1$
#350000
0$
#355000
b10 &
1$
#360000
0$
#365000
b11 &
1$
#370000
0$
#375000
1#
0"
b0 &
b11 '
1$
#380000
0$
#385000
b1 &
1$
#390000
0$
#395000
1!
0#
b0 &
b0 '
1$
#400000
0$
#405000
b1 &
1$
#410000
0$
#415000
b10 &
1$
#420000
0$
#425000
b11 &
1$
#430000
0$
#435000
b100 &
1$
#440000
0$
#445000
1#
0!
b0 &
b1 '
1$
#450000
0$
#455000
b1 &
1$
#460000
0$
#465000
1"
0#
b0 &
b10 '
1$
#470000
0$
#475000
b1 &
1$
#480000
0$
#485000
b10 &
1$
#490000
0$
#495000
b11 &
1$
#500000
0$
#505000
1#
0"
b0 &
b11 '
1$
#510000
1!
0#
b0 '
0$
1%
#515000
b1 &
1$
0%
#520000
0$
#525000
b10 &
1$
#530000
0$
#535000
b11 &
1$
#540000
0$
#545000
b100 &
1$
#550000
0$
#555000
1#
0!
b0 &
b1 '
1$
#560000
0$
#565000
b1 &
1$
#570000
0$
#575000
1"
0#
b0 &
b10 '
1$
#580000
0$
#585000
b1 &
1$
#590000
0$
#595000
b10 &
1$
#600000
0$
#605000
b11 &
1$
#610000
0$
#615000
1#
0"
b0 &
b11 '
1$
#620000
0$
#625000
b1 &
1$
#630000
0$
#635000
1!
0#
b0 &
b0 '
1$
#640000
0$
#645000
b1 &
1$
#650000
0$
#655000
b10 &
1$
#660000
0$
#665000
b11 &
1$
#670000
0$
#675000
b100 &
1$
#680000
0$
#685000
1#
0!
b0 &
b1 '
1$
#690000
0$
#695000
b1 &
1$
#700000
0$
#705000
1"
0#
b0 &
b10 '
1$
#710000
0$
#715000
b1 &
1$
#720000
0$
#725000
b10 &
1$
#730000
0$
#735000
b11 &
1$
#740000
0$
#745000
1#
0"
b0 &
b11 '
1$
#750000
0$
#755000
b1 &
1$
#760000
0$
#765000
1!
0#
b0 &
b0 '
1$
#770000
0$
#775000
b1 &
1$
#780000
0$
#785000
b10 &
1$
#790000
0$
#795000
b11 &
1$
#800000
0$
#805000
b100 &
1$
#810000
0$
#815000
1#
0!
b0 &
b1 '
1$
#820000
0$
#825000
b1 &
1$
#830000
0$
#835000
1"
0#
b0 &
b10 '
1$
#840000
0$
#845000
b1 &
1$
#850000
0$
#855000
b10 &
1$
#860000
0$
#865000
b11 &
1$
#870000
0$
#875000
1#
0"
b0 &
b11 '
1$
#880000
0$
#885000
b1 &
1$
#890000
0$
#895000
1!
0#
b0 &
b0 '
1$
#900000
0$
#905000
b1 &
1$
#910000
0$
#915000
b10 &
1$
#920000
0$
#925000
b11 &
1$
#930000
0$
#935000
b100 &
1$
#940000
0$
#945000
1#
0!
b0 &
b1 '
1$
#950000
0$
#955000
b1 &
1$
#960000
0$
#965000
1"
0#
b0 &
b10 '
1$
#970000
0$
#975000
b1 &
1$
#980000
0$
#985000
b10 &
1$
#990000
0$
#995000
b11 &
1$
#1000000
0$
#1005000
1#
0"
b0 &
b11 '
1$
#1010000
0$
#1015000
b1 &
1$
