Lab00/codigos/punto 3/Nico/Top3.v
module Top3 (
    input CLK,
    input reset,
    input start,

    input [7:0] data,

    output reg tx,
    output reg busy,
    output reg done
);
    parameter N = 8;
    parameter CLKS_PER_BIT = N;

    reg [7:0] shift_reg;
    reg [2:0] bit_count;
    reg [$clog2(CLKS_PER_BIT)-1:0] tick_cnt;

    reg [1:0] estado;

    localparam IDLE = 2'd0;
    localparam LOAD = 2'd1;
    localparam TRANSMIT = 2'd2;
    localparam DONE = 2'd3;

    always @(posedge CLK, posedge reset) begin
        if (reset) begin
            busy <= 0;
            done <= 0;
            tx = 1;
            shift_reg <= 0;
            bit_count <= 0;
            tick_cnt <= 0;
            estado <= 0;
        end else begin
            case (estado)
                IDLE: begin
                    busy <= 0;
                    done <= 0;
                    tx <= 1;
                    bit_count <= 0;
                    shift_reg <= 0;
                    tick_cnt <= 0;
                    if (start) estado <= LOAD;
                end
                LOAD: begin
                    busy <= 1;
                    done <= 0;
                    tx <= 1;
                    bit_count <= 0;
                    shift_reg <= data;
                    tick_cnt <= 0;
                    estado <= TRANSMIT;
                end
                TRANSMIT: begin
                    busy <= 1;
                    done <= 0;
                    tx <= shift_reg[0];
                    if (&tick_cnt) begin
                        if (bit_count == 3'd7) estado <= DONE;
                        else begin
                            bit_count <= bit_count + 3'd1;
                            tick_cnt <= 0;
                            shift_reg = shift_reg >> 1;
                        end
                    end else tick_cnt = tick_cnt + 3'd1;
                end
                DONE: begin
                    busy <= 0;
                    done <= 1;
                    tx <= 1;
                    bit_count <= bit_count;
                    shift_reg <= shift_reg;
                    tick_cnt <= tick_cnt;
                    estado <= IDLE;
                end
            default: begin 
                busy <= 0;
                done <= 0;
                tx <= 1;
                bit_count <= 0;
                shift_reg <= 0;
                tick_cnt <= 0;
                estado <= IDLE;
            end
            endcase
        end
    end
endmodule

Lab00/codigos/punto 3/Nico/TBtop3.v
`timescale 1ns/1ps

module TBtop3;
    reg CLK = 0;
    reg reset = 0;
    reg start = 0;
    reg [7:0] data = 0;

    wire tx;
    wire busy;
    wire done;

    Top3 uut (
        .CLK  (CLK),
        .reset(reset),
        .start(start),
        .data (data),
        .tx   (tx),
        .busy (busy),
        .done (done)
    );

    always begin
        #5 CLK = ~CLK;
    end

    initial begin
        $dumpfile("Ejer3/TBtop3.vcd");
        $dumpvars(0, TBtop3);

        #5;
        reset = 1'b1;

        #5;
        reset = 1'b0;

        #15;
        data = 8'hA5;

        #5;
        start = 1'b1;

        #10;
        start = 1'b0;

        #750;
        data = 8'h3C;

        #5;
        start = 1'b1;

        #10;
        start = 1'b0;
        
        #750;
        reset = 1;

        #10;
        reset = 0;

        #50;

        $finish;
    end
endmodule

Lab00/codigos/punto 3/Nico/TBtop3.vcd
$date
	Sun Sep 13 17:07:05 2026
$end
$version
	Icarus Verilog
$end
$timescale
	1ps
$end
$scope module TBtop3 $end
$var wire 1 ! tx $end
$var wire 1 " done $end
$var wire 1 # busy $end
$var reg 1 $ CLK $end
$var reg 8 % data [7:0] $end
$var reg 1 & reset $end
$var reg 1 ' start $end
$scope module uut $end
$var wire 1 $ CLK $end
$var wire 8 ( data [7:0] $end
$var wire 1 & reset $end
$var wire 1 ' start $end
$var parameter 32 ) CLKS_PER_BIT $end
$var parameter 2 * DONE $end
$var parameter 2 + IDLE $end
$var parameter 2 , LOAD $end
$var parameter 32 - N $end
$var parameter 2 . TRANSMIT $end
$var reg 3 / bit_count [2:0] $end
$var reg 1 # busy $end
$var reg 1 " done $end
$var reg 2 0 estado [1:0] $end
$var reg 8 1 shift_reg [7:0] $end
$var reg 3 2 tick_cnt [2:0] $end
$var reg 1 ! tx $end
$upscope $end
$upscope $end
$enddefinitions $end
$comment Show the parameter values. $end
$dumpall
b10 .
b1000 -
b1 ,
b0 +
b11 *
b1000 )
$end
#0
$dumpvars
bx 2
bx 1
bx 0
bx /
b0 (
0'
0&
b0 %
0$
x#
x"
x!
$end
#5000
b0 0
b0 2
b0 /
b0 1
0"
0#
1!
1&
1$
#10000
0&
0$
#15000
1$
#20000
0$
#25000
1$
b10100101 %
b10100101 (
#30000
0$
1'
#35000
b1 0
1$
#40000
0$
0'
#45000
b10 0
b10100101 1
1#
1$
#50000
0$
#55000
b1 2
1$
#60000
0$
#65000
b10 2
1$
#70000
0$
#75000
b11 2
1$
#80000
0$
#85000
b100 2
1$
#90000
0$
#95000
b101 2
1$
#100000
0$
#105000
b110 2
1$
#110000
0$
#115000
b111 2
1$
#120000
0$
#125000
b0 2
b1 /
b1010010 1
1$
#130000
0$
#135000
0!
b1 2
1$
#140000
0$
#145000
b10 2
1$
#150000
0$
#155000
b11 2
1$
#160000
0$
#165000
b100 2
1$
#170000
0$
#175000
b101 2
1$
#180000
0$
#185000
b110 2
1$
#190000
0$
#195000
b111 2
1$
#200000
0$
#205000
b0 2
b10 /
b101001 1
1$
#210000
0$
#215000
1!
b1 2
1$
#220000
0$
#225000
b10 2
1$
#230000
0$
#235000
b11 2
1$
#240000
0$
#245000
b100 2
1$
#250000
0$
#255000
b101 2
1$
#260000
0$
#265000
b110 2
1$
#270000
0$
#275000
b111 2
1$
#280000
0$
#285000
b0 2
b11 /
b10100 1
1$
#290000
0$
#295000
0!
b1 2
1$
#300000
0$
#305000
b10 2
1$
#310000
0$
#315000
b11 2
1$
#320000
0$
#325000
b100 2
1$
#330000
0$
#335000
b101 2
1$
#340000
0$
#345000
b110 2
1$
#350000
0$
#355000
b111 2
1$
#360000
0$
#365000
b0 2
b100 /
b1010 1
1$
#370000
0$
#375000
b1 2
1$
#380000
0$
#385000
b10 2
1$
#390000
0$
#395000
b11 2
1$
#400000
0$
#405000
b100 2
1$
#410000
0$
#415000
b101 2
1$
#420000
0$
#425000
b110 2
1$
#430000
0$
#435000
b111 2
1$
#440000
0$
#445000
b0 2
b101 /
b101 1
1$
#450000
0$
#455000
1!
b1 2
1$
#460000
0$
#465000
b10 2
1$
#470000
0$
#475000
b11 2
1$
#480000
0$
#485000
b100 2
1$
#490000
0$
#495000
b101 2
1$
#500000
0$
#505000
b110 2
1$
#510000
0$
#515000
b111 2
1$
#520000
0$
#525000
b0 2
b110 /
b10 1
1$
#530000
0$
#535000
0!
b1 2
1$
#540000
0$
#545000
b10 2
1$
#550000
0$
#555000
b11 2
1$
#560000
0$
#565000
b100 2
1$
#570000
0$
#575000
b101 2
1$
#580000
0$
#585000
b110 2
1$
#590000
0$
#595000
b111 2
1$
#600000
0$
#605000
b0 2
b111 /
b1 1
1$
#610000
0$
#615000
1!
b1 2
1$
#620000
0$
#625000
b10 2
1$
#630000
0$
#635000
b11 2
1$
#640000
0$
#645000
b100 2
1$
#650000
0$
#655000
b101 2
1$
#660000
0$
#665000
b110 2
1$
#670000
0$
#675000
b111 2
1$
#680000
0$
#685000
b11 0
1$
#690000
0$
#695000
b0 0
1"
0#
1$
#700000
0$
#705000
b0 2
b0 1
b0 /
0"
1$
#710000
0$
#715000
1$
#720000
0$
#725000
1$
#730000
0$
#735000
1$
#740000
0$
#745000
1$
#750000
0$
#755000
1$
#760000
0$
#765000
1$
#770000
0$
#775000
1$
#780000
0$
#785000
1$
#790000
0$
b111100 %
b111100 (
#795000
b1 0
1$
1'
#800000
0$
#805000
b10 0
b111100 1
1#
1$
0'
#810000
0$
#815000
0!
b1 2
1$
#820000
0$
#825000
b10 2
1$
#830000
0$
#835000
b11 2
1$
#840000
0$
#845000
b100 2
1$
#850000
0$
#855000
b101 2
1$
#860000
0$
#865000
b110 2
1$
#870000
0$
#875000
b111 2
1$
#880000
0$
#885000
b0 2
b1 /
b11110 1
1$
#890000
0$
#895000
b1 2
1$
#900000
0$
#905000
b10 2
1$
#910000
0$
#915000
b11 2
1$
#920000
0$
#925000
b100 2
1$
#930000
0$
#935000
b101 2
1$
#940000
0$
#945000
b110 2
1$
#950000
0$
#955000
b111 2
1$
#960000
0$
#965000
b0 2
b10 /
b1111 1
1$
#970000
0$
#975000
1!
b1 2
1$
#980000
0$
#985000
b10 2
1$
#990000
0$
#995000
b11 2
1$
#1000000
0$
#1005000
b100 2
1$
#1010000
0$
#1015000
b101 2
1$
#1020000
0$
#1025000
b110 2
1$
#1030000
0$
#1035000
b111 2
1$
#1040000
0$
#1045000
b0 2
b11 /
b111 1
1$
#1050000
0$
#1055000
b1 2
1$
#1060000
0$
#1065000
b10 2
1$
#1070000
0$
#1075000
b11 2
1$
#1080000
0$
#1085000
b100 2
1$
#1090000
0$
#1095000
b101 2
1$
#1100000
0$
#1105000
b110 2
1$
#1110000
0$
#1115000
b111 2
1$
#1120000
0$
#1125000
b0 2
b100 /
b11 1
1$
#1130000
0$
#1135000
b1 2
1$
#1140000
0$
#1145000
b10 2
1$
#1150000
0$
#1155000
b11 2
1$
#1160000
0$
#1165000
b100 2
1$
#1170000
0$
#1175000
b101 2
1$
#1180000
0$
#1185000
b110 2
1$
#1190000
0$
#1195000
b111 2
1$
#1200000
0$
#1205000
b0 2
b101 /
b1 1
1$
#1210000
0$
#1215000
b1 2
1$
#1220000
0$
#1225000
b10 2
1$
#1230000
0$
#1235000
b11 2
1$
#1240000
0$
#1245000
b100 2
1$
#1250000
0$
#1255000
b101 2
1$
#1260000
0$
#1265000
b110 2
1$
#1270000
0$
#1275000
b111 2
1$
#1280000
0$
#1285000
b0 2
b110 /
b0 1
1$
#1290000
0$
#1295000
0!
b1 2
1$
#1300000
0$
#1305000
b10 2
1$
#1310000
0$
#1315000
b11 2
1$
#1320000
0$
#1325000
b100 2
1$
#1330000
0$
#1335000
b101 2
1$
#1340000
0$
#1345000
b110 2
1$
#1350000
0$
#1355000
b111 2
1$
#1360000
0$
#1365000
b0 2
b111 /
1$
#1370000
0$
#1375000
b1 2
1$
#1380000
0$
#1385000
b10 2
1$
#1390000
0$
#1395000
b11 2
1$
#1400000
0$
#1405000
b100 2
1$
#1410000
0$
#1415000
b101 2
1$
#1420000
0$
#1425000
b110 2
1$
#1430000
0$
#1435000
b111 2
1$
#1440000
0$
#1445000
b11 0
1$
#1450000
0$
#1455000
b0 0
1!
1"
0#
1$
#1460000
0$
#1465000
b0 2
b0 /
0"
1$
#1470000
0$
#1475000
1$
#1480000
0$
#1485000
1$
#1490000
0$
#1495000
1$
#1500000
0$
#1505000
1$
#1510000
0$
#1515000
1$
#1520000
0$
#1525000
1$
#1530000
0$
#1535000
1$
#1540000
0$
#1545000
1$
#1550000
0$
#1555000
1$
1&
#1560000
0$
#1565000
1$
0&
